LICENSE
README.md
setup.py
cogreqs/__init__.py
cogreqs/cogreqs.py
cogreqs/exceptions.py
cogreqs/heuristics.py
cogreqs/mappings.py
cogreqs/parse.py
cogreqs/predict_template.py
cogreqs/types.py
cogreqs.egg-info/PKG-INFO
cogreqs.egg-info/SOURCES.txt
cogreqs.egg-info/dependency_links.txt
cogreqs.egg-info/entry_points.txt
cogreqs.egg-info/requires.txt
cogreqs.egg-info/top_level.txt