Metadata-Version: 2.1
Name: cogreqs
Version: 0.0.6
Summary: Automatically construct cog.yaml from a repository
Home-page: https://github.com/andreasjansson/cogreqs
License: UNKNOWN
Platform: UNKNOWN
